holograph/__init__.py
holograph/cli.py
holograph/core.py
holograph/theme.py
holograph/charts/__init__.py
holograph/charts/bar.py
holograph/charts/line.py
tanish_graph-0.1.0.dist-info/licenses/LICENSE
tanish_graph-0.1.0.dist-info/METADATA
tanish_graph-0.1.0.dist-info/WHEEL
tanish_graph-0.1.0.dist-info/entry_points.txt
tanish_graph-0.1.0.dist-info/top_level.txt
tanish_graph-0.1.0.dist-info/RECORD
