Metadata-Version: 2.4
Name: tanish-graph
Version: 0.1.0
Summary: ASCII/Unicode terminal graphs (bar/line) with a tiny CLI.
Author-email: Tanish Tirpathi <tanishtirpathi0@gmail.com>
License: MIT License
Project-URL: Homepage, https://github.com/tanishtirpathi/holograph
Project-URL: Issues, https://github.com/tanishtirpathi/holograph/issues
Keywords: ascii,terminal,graph,chart,cli
Classifier: Programming Language :: Python :: 3
Classifier: Programming Language :: Python :: 3 :: Only
Classifier: License :: OSI Approved :: MIT License
Classifier: Environment :: Console
Classifier: Topic :: Terminals
Classifier: Topic :: Utilities
Requires-Python: >=3.9
License-File: LICENSE
Provides-Extra: image
Requires-Dist: pillow>=10.0.0; extra == "image"
Dynamic: license-file
